{"MRData": {"total": "54", "ResultTable": {"Results": [{"resultId": 4401, "raceId": 224, "driverId": 69, "constructorId": 28, "number": "22", "grid": 21, "position": "\\N", "positionText": "F", "positionOrder": 21, "points": 0.0, "laps": 0, "time": "\\N", "milliseconds": "\\N", "fastestLap": "\\N", "rank": "\\N", "fastestLapTime": "\\N", "fastestLapSpeed": "\\N", "statusId": 77, "Constructor": {"constructorId": 28, "name": "Forti", "constructorName": "Forti"}}, {"resultId": 4402, "raceId": 224, "driverId": 85, "constructorId": 28, "number": "23", "grid": 22, "position": "\\N", "positionText": "F", "positionOrder": 22, "points": 0.0, "laps": 0, "time": "\\N", "milliseconds": "\\N", "fastestLap": "\\N", "rank": "\\N", "fastestLapTime": "\\N", "fastestLapSpeed": "\\N", "statusId": 77, "Constructor": {"constructorId": 28, "name": "Forti", "constructorName": "Forti"}}, {"resultId": 4413, "raceId": 225, "driverId": 69, "constructorId": 28, "number": "22", "grid": 19, "position": "11", "positionText": "11", "positionOrder": 11, "points": 0.0, "laps": 67, "time": "\\N", "milliseconds": "\\N", "fastestLap": "\\N", "rank": "\\N", "fastestLapTime": "\\N", "fastestLapSpeed": "\\N", "statusId": 14, "Constructor": {"constructorId": 28, "name": "Forti", "constructorName": "Forti"}}, {"resultId": 4421, "raceId": 225, "driverId": 85, "constructorId": 28, "number": "23", "grid": 20, "position": "\\N", "positionText": "R", "positionOrder": 19, "points": 0.0, "laps": 26, "time": "\\N", "milliseconds": "\\N", "fastestLap": "\\N", "rank": "\\N", "fastestLapTime": "\\N", "fastestLapSpeed": "\\N", "statusId": 20, "Constructor": {"constructorId": 28, "name": "Forti", "constructorName": "Forti"}}, {"resultId": 4434, "raceId": 226, "driverId": 85, "constructorId": 28, "number": "23", "grid": 22, "position": "10", "positionText": "10", "positionOrder": 10, "points": 0.0, "laps": 69, "time": "\\N", "milliseconds": "\\N", "fastestLap": "\\N", "rank": "\\N", "fastestLapTime": "\\N", "fastestLapSpeed": "\\N", "statusId": 13, "Constructor": {"constructorId": 28, "name": "Forti", "constructorName": "Forti"}}, {"resultId": 4445, "raceId": 226, "driverId": 69, "constructorId": 28, "number": "22", "grid": 21, "position": "\\N", "positionText": "R", "positionOrder": 21, "points": 0.0, "laps": 24, "time": "\\N", "milliseconds": "\\N", "fastestLap": "\\N", "rank": "\\N", "fastestLapTime": "\\N", "fastestLapSpeed": "\\N", "statusId": 4, "Constructor": {"constructorId": 28, "name": "Forti", "constructorName": "Forti"}}, {"resultId": 4467, "raceId": 227, "driverId": 85, "constructorId": 28, "number": "23", "grid": 21, "position": "\\N", "positionText": "F", "positionOrder": 21, "points": 0.0, "laps": 0, "time": "\\N", "milliseconds": "\\N", "fastestLap": "\\N", "rank": "\\N", "fastestLapTime": "\\N", "fastestLapSpeed": "\\N", "statusId": 77, "Constructor": {"constructorId": 28, "name": "Forti", "constructorName": "Forti"}}, {"resultId": 4468, "raceId": 227, "driverId": 69, "constructorId": 28, "number": "22", "grid": 22, "position": "\\N", "positionText": "F", "positionOrder": 22, "points": 0.0, "laps": 0, "time": "\\N", "milliseconds": "\\N", "fastestLap": "\\N", "rank": "\\N", "fastestLapTime": "\\N", "fastestLapSpeed": "\\N", "statusId": 77, "Constructor": {"constructorId": 28, "name": "Forti", "constructorName": "Forti"}}, {"resultId": 4478, "raceId": 228, "driverId": 69, "constructorId": 28, "number": "22", "grid": 21, "position": "10", "positionText": "10", "positionOrder": 10, "points": 0.0, "laps": 59, "time": "\\N", "milliseconds": "\\N", "fastestLap": "\\N", "rank": "\\N", "fastestLapTime": "\\N", "fastestLapSpeed": "\\N", "statusId": 14, "Constructor": {"constructorId": 28, "name": "Forti", "constructorName": "Forti"}}, {"resultId": 4490, "raceId": 228, "driverId": 85, "constructorId": 28, "number": "23", "grid": 22, "position": "\\N", "positionText": "F", "positionOrder": 22, "points": 0.0, "laps": 0, "time": "\\N", "milliseconds": "\\N", "fastestLap": "\\N", "rank": "\\N", "fastestLapTime": "\\N", "fastestLapSpeed": "\\N", "statusId": 77, "Constructor": {"constructorId": 28, "name": "Forti", "constructorName": "Forti"}}, {"resultId": 4500, "raceId": 229, "driverId": 69, "constructorId": 28, "number": "22", "grid": 21, "position": "\\N", "positionText": "R", "positionOrder": 10, "points": 0.0, "laps": 60, "time": "\\N", "milliseconds": "\\N", "fastestLap": "\\N", "rank": "\\N", "fastestLapTime": "\\N", "fastestLapSpeed": "\\N", "statusId": 4, "Constructor": {"constructorId": 28, "name": "Forti", "constructorName": "Forti"}}, {"resultId": 4512, "raceId": 229, "driverId": 85, "constructorId": 28, "number": "23", "grid": 22, "position": "\\N", "positionText": "F", "positionOrder": 22, "points": 0.0, "laps": 0, "time": "\\N", "milliseconds": "\\N", "fastestLap": "\\N", "rank": "\\N", "fastestLapTime": "\\N", "fastestLapSpeed": "\\N", "statusId": 82, "Constructor": {"constructorId": 28, "name": "Forti", "constructorName": "Forti"}}, {"resultId": 4533, "raceId": 230, "driverId": 69, "constructorId": 28, "number": "22", "grid": 21, "position": "\\N", "positionText": "F", "positionOrder": 21, "points": 0.0, "laps": 0, "time": "\\N", "milliseconds": "\\N", "fastestLap": "\\N", "rank": "\\N", "fastestLapTime": "\\N", "fastestLapSpeed": "\\N", "statusId": 77, "Constructor": {"constructorId": 28, "name": "Forti", "constructorName": "Forti"}}, {"resultId": 4534, "raceId": 230, "driverId": 85, "constructorId": 28, "number": "23", "grid": 22, "position": "\\N", "positionText": "F", "positionOrder": 22, "points": 0.0, "laps": 0, "time": "\\N", "milliseconds": "\\N", "fastestLap": "\\N", "rank": "\\N", "fastestLapTime": "\\N", "fastestLapSpeed": "\\N", "statusId": 77, "Constructor": {"constructorId": 28, "name": "Forti", "constructorName": "Forti"}}, {"resultId": 4544, "raceId": 231, "driverId": 69, "constructorId": 28, "number": "22", "grid": 20, "position": "\\N", "positionText": "R", "positionOrder": 10, "points": 0.0, "laps": 44, "time": "\\N", "milliseconds": "\\N", "fastestLap": "\\N", "rank": "\\N", "fastestLapTime": "\\N", "fastestLapSpeed": "\\N", "statusId": 6, "Constructor": {"constructorId": 28, "name": "Forti", "constructorName": "Forti"}}, {"resultId": 4551, "raceId": 231, "driverId": 85, "constructorId": 28, "number": "23", "grid": 22, "position": "\\N", "positionText": "R", "positionOrder": 17, "points": 0.0, "laps": 22, "time": "\\N", "milliseconds": "\\N", "fastestLap": "\\N", "rank": "\\N", "fastestLapTime": "\\N", "fastestLapSpeed": "\\N", "statusId": 10, "Constructor": {"constructorId": 28, "name": "Forti", "constructorName": "Forti"}}, {"resultId": 4572, "raceId": 232, "driverId": 69, "constructorId": 28, "number": "22", "grid": 20, "position": "\\N", "positionText": "R", "positionOrder": 16, "points": 0.0, "laps": 29, "time": "\\N", "milliseconds": "\\N", "fastestLap": "\\N", "rank": "\\N", "fastestLapTime": "\\N", "fastestLapSpeed": "\\N", "statusId": 69, "Constructor": {"constructorId": 28, "name": "Forti", "constructorName": "Forti"}}, {"resultId": 4577, "raceId": 232, "driverId": 85, "constructorId": 28, "number": "23", "grid": 21, "position": "\\N", "positionText": "R", "positionOrder": 21, "points": 0.0, "laps": 2, "time": "\\N", "milliseconds": "\\N", "fastestLap": "\\N", "rank": "\\N", "fastestLapTime": "\\N", "fastestLapSpeed": "\\N", "statusId": 10, "Constructor": {"constructorId": 28, "name": "Forti", "constructorName": "Forti"}}, {"resultId": 4599, "raceId": 233, "driverId": 85, "constructorId": 28, "number": "23", "grid": 21, "position": "\\N", "positionText": "F", "positionOrder": 21, "points": 0.0, "laps": 0, "time": "\\N", "milliseconds": "\\N", "fastestLap": "\\N", "rank": "\\N", "fastestLapTime": "\\N", "fastestLapSpeed": "\\N", "statusId": 81, "Constructor": {"constructorId": 28, "name": "Forti", "constructorName": "Forti"}}, {"resultId": 4600, "raceId": 233, "driverId": 69, "constructorId": 28, "number": "22", "grid": 22, "position": "\\N", "positionText": "F", "positionOrder": 22, "points": 0.0, "laps": 0, "time": "\\N", "milliseconds": "\\N", "fastestLap": "\\N", "rank": "\\N", "fastestLapTime": "\\N", "fastestLapSpeed": "\\N", "statusId": 81, "Constructor": {"constructorId": 28, "name": "Forti", "constructorName": "Forti"}}, {"resultId": 4730, "raceId": 240, "driverId": 64, "constructorId": 28, "number": "21", "grid": 25, "position": "10", "positionText": "10", "positionOrder": 10, "points": 0.0, "laps": 64, "time": "\\N", "milliseconds": "\\N", "fastestLap": "\\N", "rank": "\\N", "fastestLapTime": "\\N", "fastestLapSpeed": "\\N", "statusId": 17, "Constructor": {"constructorId": 28, "name": "Forti", "constructorName": "Forti"}}, {"resultId": 4734, "raceId": 240, "driverId": 90, "constructorId": 28, "number": "22", "grid": 23, "position": "\\N", "positionText": "R", "positionOrder": 14, "points": 0.0, "laps": 47, "time": "\\N", "milliseconds": "\\N", "fastestLap": "\\N", "rank": "\\N", "fastestLapTime": "\\N", "fastestLapSpeed": "\\N", "statusId": 20, "Constructor": {"constructorId": 28, "name": "Forti", "constructorName": "Forti"}}, {"resultId": 4756, "raceId": 241, "driverId": 64, "constructorId": 28, "number": "21", "grid": 25, "position": "\\N", "positionText": "N", "positionOrder": 10, "points": 0.0, "laps": 63, "time": "\\N", "milliseconds": "\\N", "fastestLap": "\\N", "rank": "\\N", "fastestLapTime": "\\N", "fastestLapSpeed": "\\N", "statusId": 62, "Constructor": {"constructorId": 28, "name": "Forti", "constructorName": "Forti"}}, {"resultId": 4757, "raceId": 241, "driverId": 90, "constructorId": 28, "number": "22", "grid": 24, "position": "\\N", "positionText": "N", "positionOrder": 11, "points": 0.0, "laps": 63, "time": "\\N", "milliseconds": "\\N", "fastestLap": "\\N", "rank": "\\N", "fastestLapTime": "\\N", "fastestLapSpeed": "\\N", "statusId": 62, "Constructor": {"constructorId": 28, "name": "Forti", "constructorName": "Forti"}}, {"resultId": 4787, "raceId": 242, "driverId": 64, "constructorId": 28, "number": "21", "grid": 26, "position": "\\N", "positionText": "N", "positionOrder": 15, "points": 0.0, "laps": 56, "time": "\\N", "milliseconds": "\\N", "fastestLap": "\\N", "rank": "\\N", "fastestLapTime": "\\N", "fastestLapSpeed": "\\N", "statusId": 62, "Constructor": {"constructorId": 28, "name": "Forti", "constructorName": "Forti"}}, {"resultId": 4788, "raceId": 242, "driverId": 90, "constructorId": 28, "number": "22", "grid": 25, "position": "\\N", "positionText": "N", "positionOrder": 16, "points": 0.0, "laps": 56, "time": "\\N", "milliseconds": "\\N", "fastestLap": "\\N", "rank": "\\N", "fastestLapTime": "\\N", "fastestLapSpeed": "\\N", "statusId": 62, "Constructor": {"constructorId": 28, "name": "Forti", "constructorName": "Forti"}}, {"resultId": 4819, "raceId": 243, "driverId": 90, "constructorId": 28, "number": "22", "grid": 25, "position": "\\N", "positionText": "R", "positionOrder": 21, "points": 0.0, "laps": 39, "time": "\\N", "milliseconds": "\\N", "fastestLap": "\\N", "rank": "\\N", "fastestLapTime": "\\N", "fastestLapSpeed": "\\N", "statusId": 25, "Constructor": {"constructorId": 28, "name": "Forti", "constructorName": "Forti"}}, {"resultId": 4823, "raceId": 243, "driverId": 64, "constructorId": 28, "number": "21", "grid": 26, "position": "\\N", "positionText": "R", "positionOrder": 25, "points": 0.0, "laps": 17, "time": "\\N", "milliseconds": "\\N", "fastestLap": "\\N", "rank": "\\N", "fastestLapTime": "\\N", "fastestLapSpeed": "\\N", "statusId": 6, "Constructor": {"constructorId": 28, "name": "Forti", "constructorName": "Forti"}}, {"resultId": 4834, "raceId": 244, "driverId": 64, "constructorId": 28, "number": "21", "grid": 22, "position": "10", "positionText": "10", "positionOrder": 10, "points": 0.0, "laps": 72, "time": "\\N", "milliseconds": "\\N", "fastestLap": "\\N", "rank": "\\N", "fastestLapTime": "\\N", "fastestLapSpeed": "\\N", "statusId": 16, "Constructor": {"constructorId": 28, "name": "Forti", "constructorName": "Forti"}}, {"resultId": 4847, "raceId": 244, "driverId": 90, "constructorId": 28, "number": "22", "grid": 24, "position": "\\N", "positionText": "R", "positionOrder": 23, "points": 0.0, "laps": 9, "time": "\\N", "milliseconds": "\\N", "fastestLap": "\\N", "rank": "\\N", "fastestLapTime": "\\N", "fastestLapSpeed": "\\N", "statusId": 23, "Constructor": {"constructorId": 28, "name": "Forti", "constructorName": "Forti"}}, {"resultId": 4863, "raceId": 245, "driverId": 90, "constructorId": 28, "number": "22", "grid": 23, "position": "\\N", "positionText": "R", "positionOrder": 13, "points": 0.0, "laps": 54, "time": "\\N", "milliseconds": "\\N", "fastestLap": "\\N", "rank": "\\N", "fastestLapTime": "\\N", "fastestLapSpeed": "\\N", "statusId": 69, "Constructor": {"constructorId": 28, "name": "Forti", "constructorName": "Forti"}}, {"resultId": 4869, "raceId": 245, "driverId": 64, "constructorId": 28, "number": "21", "grid": 24, "position": "\\N", "positionText": "R", "positionOrder": 19, "points": 0.0, "laps": 26, "time": "\\N", "milliseconds": "\\N", "fastestLap": "\\N", "rank": "\\N", "fastestLapTime": "\\N", "fastestLapSpeed": "\\N", "statusId": 6, "Constructor": {"constructorId": 28, "name": "Forti", "constructorName": "Forti"}}, {"resultId": 4890, "raceId": 246, "driverId": 90, "constructorId": 28, "number": "22", "grid": 24, "position": "16", "positionText": "16", "positionOrder": 16, "points": 0.0, "laps": 66, "time": "\\N", "milliseconds": "\\N", "fastestLap": "\\N", "rank": "\\N", "fastestLapTime": "\\N", "fastestLapSpeed": "\\N", "statusId": 16, "Constructor": {"constructorId": 28, "name": "Forti", "constructorName": "Forti"}}, {"resultId": 4898, "raceId": 246, "driverId": 64, "constructorId": 28, "number": "21", "grid": 23, "position": "\\N", "positionText": "R", "positionOrder": 24, "points": 0.0, "laps": 0, "time": "\\N", "milliseconds": "\\N", "fastestLap": "\\N", "rank": "\\N", "fastestLapTime": "\\N", "fastestLapSpeed": "\\N", "statusId": 20, "Constructor": {"constructorId": 28, "name": "Forti", "constructorName": "Forti"}}, {"resultId": 4911, "raceId": 247, "driverId": 90, "constructorId": 28, "number": "22", "grid": 22, "position": "\\N", "positionText": "R", "positionOrder": 13, "points": 0.0, "laps": 48, "time": "\\N", "milliseconds": "\\N", "fastestLap": "\\N", "rank": "\\N", "fastestLapTime": "\\N", "fastestLapSpeed": "\\N", "statusId": 5, "Constructor": {"constructorId": 28, "name": "Forti", "constructorName": "Forti"}}, {"resultId": 4921, "raceId": 247, "driverId": 64, "constructorId": 28, "number": "21", "grid": 20, "position": "\\N", "positionText": "R", "positionOrder": 23, "points": 0.0, "laps": 13, "time": "\\N", "milliseconds": "\\N", "fastestLap": "\\N", "rank": "\\N", "fastestLapTime": "\\N", "fastestLapSpeed": "\\N", "statusId": 6, "Constructor": {"constructorId": 28, "name": "Forti", "constructorName": "Forti"}}, {"resultId": 4936, "raceId": 248, "driverId": 90, "constructorId": 28, "number": "22", "grid": 22, "position": "\\N", "positionText": "R", "positionOrder": 14, "points": 0.0, "laps": 27, "time": "\\N", "milliseconds": "\\N", "fastestLap": "\\N", "rank": "\\N", "fastestLapTime": "\\N", "fastestLapSpeed": "\\N", "statusId": 86, "Constructor": {"constructorId": 28, "name": "Forti", "constructorName": "Forti"}}, {"resultId": 4943, "raceId": 248, "driverId": 64, "constructorId": 28, "number": "21", "grid": 21, "position": "\\N", "positionText": "R", "positionOrder": 21, "points": 0.0, "laps": 8, "time": "\\N", "milliseconds": "\\N", "fastestLap": "\\N", "rank": "\\N", "fastestLapTime": "\\N", "fastestLapSpeed": "\\N", "statusId": 23, "Constructor": {"constructorId": 28, "name": "Forti", "constructorName": "Forti"}}, {"resultId": 4966, "raceId": 249, "driverId": 64, "constructorId": 28, "number": "21", "grid": 23, "position": "\\N", "positionText": "R", "positionOrder": 20, "points": 0.0, "laps": 32, "time": "\\N", "milliseconds": "\\N", "fastestLap": "\\N", "rank": "\\N", "fastestLapTime": "\\N", "fastestLapSpeed": "\\N", "statusId": 5, "Constructor": {"constructorId": 28, "name": "Forti", "constructorName": "Forti"}}, {"resultId": 4968, "raceId": 249, "driverId": 90, "constructorId": 28, "number": "22", "grid": 21, "position": "\\N", "positionText": "R", "positionOrder": 22, "points": 0.0, "laps": 8, "time": "\\N", "milliseconds": "\\N", "fastestLap": "\\N", "rank": "\\N", "fastestLapTime": "\\N", "fastestLapSpeed": "\\N", "statusId": 6, "Constructor": {"constructorId": 28, "name": "Forti", "constructorName": "Forti"}}, {"resultId": 4983, "raceId": 250, "driverId": 64, "constructorId": 28, "number": "21", "grid": 24, "position": "13", "positionText": "13", "positionOrder": 13, "points": 0.0, "laps": 42, "time": "\\N", "milliseconds": "\\N", "fastestLap": "\\N", "rank": "\\N", "fastestLapTime": "\\N", "fastestLapSpeed": "\\N", "statusId": 12, "Constructor": {"constructorId": 28, "name": "Forti", "constructorName": "Forti"}}, {"resultId": 4984, "raceId": 250, "driverId": 90, "constructorId": 28, "number": "22", "grid": 22, "position": "14", "positionText": "14", "positionOrder": 14, "points": 0.0, "laps": 42, "time": "\\N", "milliseconds": "\\N", "fastestLap": "\\N", "rank": "\\N", "fastestLapTime": "\\N", "fastestLapSpeed": "\\N", "statusId": 12, "Constructor": {"constructorId": 28, "name": "Forti", "constructorName": "Forti"}}, {"resultId": 5003, "raceId": 251, "driverId": 64, "constructorId": 28, "number": "21", "grid": 23, "position": "9", "positionText": "9", "positionOrder": 9, "points": 0.0, "laps": 50, "time": "\\N", "milliseconds": "\\N", "fastestLap": "\\N", "rank": "\\N", "fastestLapTime": "\\N", "fastestLapSpeed": "\\N", "statusId": 13, "Constructor": {"constructorId": 28, "name": "Forti", "constructorName": "Forti"}}, {"resultId": 5018, "raceId": 251, "driverId": 90, "constructorId": 28, "number": "22", "grid": 22, "position": "\\N", "positionText": "R", "positionOrder": 24, "points": 0.0, "laps": 0, "time": "\\N", "milliseconds": "\\N", "fastestLap": "\\N", "rank": "\\N", "fastestLapTime": "\\N", "fastestLapSpeed": "\\N", "statusId": 3, "Constructor": {"constructorId": 28, "name": "Forti", "constructorName": "Forti"}}, {"resultId": 5034, "raceId": 252, "driverId": 64, "constructorId": 28, "number": "21", "grid": 22, "position": "16", "positionText": "16", "positionOrder": 16, "points": 0.0, "laps": 66, "time": "\\N", "milliseconds": "\\N", "fastestLap": "\\N", "rank": "\\N", "fastestLapTime": "\\N", "fastestLapSpeed": "\\N", "statusId": 15, "Constructor": {"constructorId": 28, "name": "Forti", "constructorName": "Forti"}}, {"resultId": 5035, "raceId": 252, "driverId": 90, "constructorId": 28, "number": "22", "grid": 23, "position": "17", "positionText": "17", "positionOrder": 17, "points": 0.0, "laps": 64, "time": "\\N", "milliseconds": "\\N", "fastestLap": "\\N", "rank": "\\N", "fastestLapTime": "\\N", "fastestLapSpeed": "\\N", "statusId": 17, "Constructor": {"constructorId": 28, "name": "Forti", "constructorName": "Forti"}}, {"resultId": 5055, "raceId": 253, "driverId": 64, "constructorId": 28, "number": "21", "grid": 22, "position": "13", "positionText": "13", "positionOrder": 13, "points": 0.0, "laps": 62, "time": "\\N", "milliseconds": "\\N", "fastestLap": "\\N", "rank": "\\N", "fastestLapTime": "\\N", "fastestLapSpeed": "\\N", "statusId": 15, "Constructor": {"constructorId": 28, "name": "Forti", "constructorName": "Forti"}}, {"resultId": 5062, "raceId": 253, "driverId": 90, "constructorId": 28, "number": "22", "grid": 23, "position": "\\N", "positionText": "R", "positionOrder": 20, "points": 0.0, "laps": 22, "time": "\\N", "milliseconds": "\\N", "fastestLap": "\\N", "rank": "\\N", "fastestLapTime": "\\N", "fastestLapSpeed": "\\N", "statusId": 86, "Constructor": {"constructorId": 28, "name": "Forti", "constructorName": "Forti"}}, {"resultId": 5082, "raceId": 254, "driverId": 90, "constructorId": 28, "number": "22", "grid": 22, "position": "16", "positionText": "16", "positionOrder": 16, "points": 0.0, "laps": 78, "time": "\\N", "milliseconds": "\\N", "fastestLap": "\\N", "rank": "\\N", "fastestLapTime": "\\N", "fastestLapSpeed": "\\N", "statusId": 15, "Constructor": {"constructorId": 28, "name": "Forti", "constructorName": "Forti"}}, {"resultId": 5083, "raceId": 254, "driverId": 64, "constructorId": 28, "number": "21", "grid": 21, "position": "17", "positionText": "17", "positionOrder": 17, "points": 0.0, "laps": 77, "time": "\\N", "milliseconds": "\\N", "fastestLap": "\\N", "rank": "\\N", "fastestLapTime": "\\N", "fastestLapSpeed": "\\N", "statusId": 16, "Constructor": {"constructorId": 28, "name": "Forti", "constructorName": "Forti"}}, {"resultId": 5105, "raceId": 255, "driverId": 64, "constructorId": 28, "number": "21", "grid": 20, "position": "\\N", "positionText": "R", "positionOrder": 15, "points": 0.0, "laps": 32, "time": "\\N", "milliseconds": "\\N", "fastestLap": "\\N", "rank": "\\N", "fastestLapTime": "\\N", "fastestLapSpeed": "\\N", "statusId": 20, "Constructor": {"constructorId": 28, "name": "Forti", "constructorName": "Forti"}}, {"resultId": 5112, "raceId": 255, "driverId": 90, "constructorId": 28, "number": "22", "grid": 21, "position": "\\N", "positionText": "R", "positionOrder": 22, "points": 0.0, "laps": 1, "time": "\\N", "milliseconds": "\\N", "fastestLap": "\\N", "rank": "\\N", "fastestLapTime": "\\N", "fastestLapSpeed": "\\N", "statusId": 6, "Constructor": {"constructorId": 28, "name": "Forti", "constructorName": "Forti"}}, {"resultId": 5121, "raceId": 256, "driverId": 64, "constructorId": 28, "number": "21", "grid": 21, "position": "7", "positionText": "7", "positionOrder": 7, "points": 0.0, "laps": 77, "time": "\\N", "milliseconds": "\\N", "fastestLap": "\\N", "rank": "\\N", "fastestLapTime": "\\N", "fastestLapSpeed": "\\N", "statusId": 14, "Constructor": {"constructorId": 28, "name": "Forti", "constructorName": "Forti"}}, {"resultId": 5131, "raceId": 256, "driverId": 90, "constructorId": 28, "number": "22", "grid": 20, "position": "\\N", "positionText": "R", "positionOrder": 17, "points": 0.0, "laps": 21, "time": "\\N", "milliseconds": "\\N", "fastestLap": "\\N", "rank": "\\N", "fastestLapTime": "\\N", "fastestLapSpeed": "\\N", "statusId": 20, "Constructor": {"constructorId": 28, "name": "Forti", "constructorName": "Forti"}}]}}}