[{"resultId": 7634, "raceId": 5, "driverId": 18, "constructorId": 23, "number": "22", "grid": 1, "position": "1", "positionText": "1", "positionOrder": 1, "points": 10.0, "laps": 66, "time": "1:37:19.202", "milliseconds": "5839202", "fastestLap": "17", "rank": "2", "fastestLapTime": "1:22.899", "fastestLapSpeed": "202.149", "statusId": 1}, {"resultId": 7635, "raceId": 5, "driverId": 22, "constructorId": 23, "number": "23", "grid": 3, "position": "2", "positionText": "2", "positionOrder": 2, "points": 8.0, "laps": 66, "time": "+13.056", "milliseconds": "5852258", "fastestLap": "28", "rank": "1", "fastestLapTime": "1:22.762", "fastestLapSpeed": "202.484", "statusId": 1}, {"resultId": 7636, "raceId": 5, "driverId": 17, "constructorId": 9, "number": "14", "grid": 5, "position": "3", "positionText": "3", "positionOrder": 3, "points": 6.0, "laps": 66, "time": "+13.924", "milliseconds": "5853126", "fastestLap": "18", "rank": "5", "fastestLapTime": "1:23.112", "fastestLapSpeed": "201.631", "statusId": 1}, {"resultId": 7637, "raceId": 5, "driverId": 20, "constructorId": 9, "number": "15", "grid": 2, "position": "4", "positionText": "4", "positionOrder": 4, "points": 5.0, "laps": 66, "time": "+18.941", "milliseconds": "5858143", "fastestLap": "41", "rank": "4", "fastestLapTime": "1:23.090", "fastestLapSpeed": "201.684", "statusId": 1}, {"resultId": 7638, "raceId": 5, "driverId": 4, "constructorId": 4, "number": "7", "grid": 8, "position": "5", "positionText": "5", "positionOrder": 5, "points": 4.0, "laps": 66, "time": "+43.166", "milliseconds": "5882368", "fastestLap": "14", "rank": "6", "fastestLapTime": "1:23.420", "fastestLapSpeed": "200.887", "statusId": 1}, {"resultId": 7639, "raceId": 5, "driverId": 13, "constructorId": 6, "number": "3", "grid": 4, "position": "6", "positionText": "6", "positionOrder": 6, "points": 3.0, "laps": 66, "time": "+50.827", "milliseconds": "5890029", "fastestLap": "14", "rank": "3", "fastestLapTime": "1:23.089", "fastestLapSpeed": "201.687", "statusId": 1}, {"resultId": 7640, "raceId": 5, "driverId": 2, "constructorId": 2, "number": "6", "grid": 13, "position": "7", "positionText": "7", "positionOrder": 7, "points": 2.0, "laps": 66, "time": "+52.312", "milliseconds": "5891514", "fastestLap": "29", "rank": "10", "fastestLapTime": "1:23.878", "fastestLapSpeed": "199.790", "statusId": 1}, {"resultId": 7641, "raceId": 5, "driverId": 3, "constructorId": 3, "number": "16", "grid": 9, "position": "8", "positionText": "8", "positionOrder": 8, "points": 1.0, "laps": 66, "time": "+1:05.211", "milliseconds": "5904413", "fastestLap": "24", "rank": "7", "fastestLapTime": "1:23.621", "fastestLapSpeed": "200.404", "statusId": 1}, {"resultId": 7642, "raceId": 5, "driverId": 1, "constructorId": 1, "number": "1", "grid": 14, "position": "9", "positionText": "9", "positionOrder": 9, "points": 0.0, "laps": 65, "time": "\\N", "milliseconds": "\\N", "fastestLap": "29", "rank": "9", "fastestLapTime": "1:23.839", "fastestLapSpeed": "199.883", "statusId": 11}, {"resultId": 7643, "raceId": 5, "driverId": 10, "constructorId": 7, "number": "10", "grid": 6, "position": "10", "positionText": "10", "positionOrder": 10, "points": 0.0, "laps": 65, "time": "\\N", "milliseconds": "\\N", "fastestLap": "44", "rank": "12", "fastestLapTime": "1:24.134", "fastestLapSpeed": "199.182", "statusId": 11}, {"resultId": 7644, "raceId": 5, "driverId": 9, "constructorId": 2, "number": "5", "grid": 10, "position": "11", "positionText": "11", "positionOrder": 11, "points": 0.0, "laps": 65, "time": "\\N", "milliseconds": "\\N", "fastestLap": "26", "rank": "11", "fastestLapTime": "1:24.078", "fastestLapSpeed": "199.314", "statusId": 11}, {"resultId": 7645, "raceId": 5, "driverId": 12, "constructorId": 4, "number": "8", "grid": 12, "position": "12", "positionText": "12", "positionOrder": 12, "points": 0.0, "laps": 65, "time": "\\N", "milliseconds": "\\N", "fastestLap": "41", "rank": "14", "fastestLapTime": "1:24.286", "fastestLapSpeed": "198.823", "statusId": 11}, {"resultId": 7646, "raceId": 5, "driverId": 6, "constructorId": 3, "number": "17", "grid": 11, "position": "13", "positionText": "13", "positionOrder": 13, "points": 0.0, "laps": 65, "time": "\\N", "milliseconds": "\\N", "fastestLap": "38", "rank": "13", "fastestLapTime": "1:24.155", "fastestLapSpeed": "199.132", "statusId": 11}, {"resultId": 7647, "raceId": 5, "driverId": 21, "constructorId": 10, "number": "21", "grid": 20, "position": "14", "positionText": "14", "positionOrder": 14, "points": 0.0, "laps": 65, "time": "\\N", "milliseconds": "\\N", "fastestLap": "63", "rank": "8", "fastestLapTime": "1:23.796", "fastestLapSpeed": "199.985", "statusId": 11}, {"resultId": 7648, "raceId": 5, "driverId": 8, "constructorId": 6, "number": "4", "grid": 16, "position": "\\N", "positionText": "R", "positionOrder": 15, "points": 0.0, "laps": 17, "time": "\\N", "milliseconds": "\\N", "fastestLap": "16", "rank": "15", "fastestLapTime": "1:24.490", "fastestLapSpeed": "198.342", "statusId": 9}, {"resultId": 7649, "raceId": 5, "driverId": 5, "constructorId": 1, "number": "2", "grid": 18, "position": "\\N", "positionText": "R", "positionOrder": 16, "points": 0.0, "laps": 7, "time": "\\N", "milliseconds": "\\N", "fastestLap": "6", "rank": "16", "fastestLapTime": "1:28.719", "fastestLapSpeed": "188.888", "statusId": 6}, {"resultId": 7650, "raceId": 5, "driverId": 15, "constructorId": 7, "number": "9", "grid": 7, "position": "\\N", "positionText": "R", "positionOrder": 17, "points": 0.0, "laps": 0, "time": "\\N", "milliseconds": "\\N", "fastestLap": "\\N", "rank": "\\N", "fastestLapTime": "\\N", "fastestLapSpeed": "\\N", "statusId": 4}, {"resultId": 7651, "raceId": 5, "driverId": 67, "constructorId": 5, "number": "12", "grid": 15, "position": "\\N", "positionText": "R", "positionOrder": 18, "points": 0.0, "laps": 0, "time": "\\N", "milliseconds": "\\N", "fastestLap": "\\N", "rank": "\\N", "fastestLapTime": "\\N", "fastestLapSpeed": "\\N", "statusId": 4}, {"resultId": 7652, "raceId": 5, "driverId": 7, "constructorId": 5, "number": "11", "grid": 17, "position": "\\N", "positionText": "R", "positionOrder": 19, "points": 0.0, "laps": 0, "time": "\\N", "milliseconds": "\\N", "fastestLap": "\\N", "rank": "\\N", "fastestLapTime": "\\N", "fastestLapSpeed": "\\N", "statusId": 4}, {"resultId": 7653, "raceId": 5, "driverId": 16, "constructorId": 10, "number": "20", "grid": 19, "position": "\\N", "positionText": "R", "positionOrder": 20, "points": 0.0, "laps": 0, "time": "\\N", "milliseconds": "\\N", "fastestLap": "\\N", "rank": "\\N", "fastestLapTime": "\\N", "fastestLapSpeed": "\\N", "statusId": 4}]