{"MRData": {"RaceTable": {"Races": {"Results": [{"resultId": 8772, "raceId": 381, "driverId": 102, "constructorId": 1, "number": "12", "grid": 1, "position": "1", "positionText": "1", "positionOrder": 1, "points": 9.0, "laps": 76, "time": "1:57:47.081", "milliseconds": "7067081", "fastestLap": "\\N", "rank": "\\N", "fastestLapTime": "\\N", "fastestLapSpeed": "\\N", "statusId": 1, "name": "McLaren"}, {"resultId": 8773, "raceId": 381, "driverId": 117, "constructorId": 1, "number": "11", "grid": 7, "position": "2", "positionText": "2", "positionOrder": 2, "points": 6.0, "laps": 76, "time": "+0.529", "milliseconds": "7067610", "fastestLap": "\\N", "rank": "\\N", "fastestLapTime": "\\N", "fastestLapSpeed": "\\N", "statusId": 1, "name": "McLaren"}, {"resultId": 8774, "raceId": 381, "driverId": 123, "constructorId": 22, "number": "20", "grid": 3, "position": "3", "positionText": "3", "positionOrder": 3, "points": 4.0, "laps": 76, "time": "+31.410", "milliseconds": "7098491", "fastestLap": "\\N", "rank": "\\N", "fastestLapTime": "\\N", "fastestLapSpeed": "\\N", "statusId": 1, "name": "Benetton"}, {"resultId": 8775, "raceId": 381, "driverId": 77, "constructorId": 6, "number": "28", "grid": 9, "position": "4", "positionText": "4", "positionOrder": 4, "points": 3.0, "laps": 76, "time": "+1:28.670", "milliseconds": "7155751", "fastestLap": "\\N", "rank": "\\N", "fastestLapTime": "\\N", "fastestLapSpeed": "\\N", "statusId": 1, "name": "Ferrari"}, {"resultId": 8776, "raceId": 381, "driverId": 127, "constructorId": 37, "number": "15", "grid": 8, "position": "5", "positionText": "5", "positionOrder": 5, "points": 2.0, "laps": 75, "time": "\\N", "milliseconds": "\\N", "fastestLap": "\\N", "rank": "\\N", "fastestLapTime": "\\N", "fastestLapSpeed": "\\N", "statusId": 11, "name": "March"}, {"resultId": 8777, "raceId": 381, "driverId": 119, "constructorId": 3, "number": "6", "grid": 6, "position": "6", "positionText": "6", "positionOrder": 6, "points": 1.0, "laps": 75, "time": "\\N", "milliseconds": "\\N", "fastestLap": "\\N", "rank": "\\N", "fastestLapTime": "\\N", "fastestLapSpeed": "\\N", "statusId": 11, "name": "Williams"}, {"resultId": 8778, "raceId": 381, "driverId": 138, "constructorId": 32, "number": "2", "grid": 19, "position": "7", "positionText": "7", "positionOrder": 7, "points": 0.0, "laps": 73, "time": "\\N", "milliseconds": "\\N", "fastestLap": "\\N", "rank": "\\N", "fastestLapTime": "\\N", "fastestLapSpeed": "\\N", "statusId": 13, "name": "Team Lotus"}, {"resultId": 8779, "raceId": 381, "driverId": 137, "constructorId": 32, "number": "1", "grid": 13, "position": "8", "positionText": "8", "positionOrder": 8, "points": 0.0, "laps": 73, "time": "\\N", "milliseconds": "\\N", "fastestLap": "\\N", "rank": "\\N", "fastestLapTime": "\\N", "fastestLapSpeed": "\\N", "statusId": 13, "name": "Team Lotus"}, {"resultId": 8780, "raceId": 381, "driverId": 114, "constructorId": 33, "number": "29", "grid": 17, "position": "9", "positionText": "9", "positionOrder": 9, "points": 0.0, "laps": 73, "time": "\\N", "milliseconds": "\\N", "fastestLap": "\\N", "rank": "\\N", "fastestLapTime": "\\N", "fastestLapSpeed": "\\N", "statusId": 13, "name": "Larrousse"}, {"resultId": 8781, "raceId": 381, "driverId": 159, "constructorId": 18, "number": "24", "grid": 11, "position": "10", "positionText": "10", "positionOrder": 10, "points": 0.0, "laps": 72, "time": "\\N", "milliseconds": "\\N", "fastestLap": "\\N", "rank": "\\N", "fastestLapTime": "\\N", "fastestLapSpeed": "\\N", "statusId": 14, "name": "Minardi"}, {"resultId": 8782, "raceId": 381, "driverId": 131, "constructorId": 44, "number": "33", "grid": 26, "position": "11", "positionText": "11", "positionOrder": 11, "points": 0.0, "laps": 72, "time": "\\N", "milliseconds": "\\N", "fastestLap": "\\N", "rank": "\\N", "fastestLapTime": "\\N", "fastestLapSpeed": "\\N", "statusId": 14, "name": "Euro Brun"}, {"resultId": 8783, "raceId": 381, "driverId": 112, "constructorId": 33, "number": "30", "grid": 20, "position": "12", "positionText": "12", "positionOrder": 12, "points": 0.0, "laps": 72, "time": "\\N", "milliseconds": "\\N", "fastestLap": "\\N", "rank": "\\N", "fastestLapTime": "\\N", "fastestLapSpeed": "\\N", "statusId": 14, "name": "Larrousse"}, {"resultId": 8784, "raceId": 381, "driverId": 99, "constructorId": 42, "number": "31", "grid": 22, "position": "13", "positionText": "13", "positionOrder": 13, "points": 0.0, "laps": 71, "time": "\\N", "milliseconds": "\\N", "fastestLap": "\\N", "rank": "\\N", "fastestLapTime": "\\N", "fastestLapSpeed": "\\N", "statusId": 15, "name": "Coloni"}, {"resultId": 8785, "raceId": 381, "driverId": 118, "constructorId": 21, "number": "17", "grid": 12, "position": "\\N", "positionText": "R", "positionOrder": 14, "points": 0.0, "laps": 65, "time": "\\N", "milliseconds": "\\N", "fastestLap": "\\N", "rank": "\\N", "fastestLapTime": "\\N", "fastestLapSpeed": "\\N", "statusId": 23, "name": "Arrows"}, {"resultId": 8786, "raceId": 381, "driverId": 95, "constructorId": 3, "number": "5", "grid": 2, "position": "\\N", "positionText": "R", "positionOrder": 15, "points": 0.0, "laps": 60, "time": "\\N", "milliseconds": "\\N", "fastestLap": "\\N", "rank": "\\N", "fastestLapTime": "\\N", "fastestLapSpeed": "\\N", "statusId": 100, "name": "Williams"}, {"resultId": 8787, "raceId": 381, "driverId": 158, "constructorId": 21, "number": "18", "grid": 14, "position": "\\N", "positionText": "R", "positionOrder": 16, "points": 0.0, "laps": 55, "time": "\\N", "milliseconds": "\\N", "fastestLap": "\\N", "rank": "\\N", "fastestLapTime": "\\N", "fastestLapSpeed": "\\N", "statusId": 23, "name": "Arrows"}, {"resultId": 8788, "raceId": 381, "driverId": 105, "constructorId": 6, "number": "27", "grid": 15, "position": "\\N", "positionText": "R", "positionOrder": 17, "points": 0.0, "laps": 40, "time": "\\N", "milliseconds": "\\N", "fastestLap": "\\N", "rank": "\\N", "fastestLapTime": "\\N", "fastestLapSpeed": "\\N", "statusId": 10, "name": "Ferrari"}, {"resultId": 8789, "raceId": 381, "driverId": 163, "constructorId": 27, "number": "25", "grid": 25, "position": "\\N", "positionText": "R", "positionOrder": 18, "points": 0.0, "laps": 32, "time": "\\N", "milliseconds": "\\N", "fastestLap": "\\N", "rank": "\\N", "fastestLapTime": "\\N", "fastestLapSpeed": "\\N", "statusId": 5, "name": "Ligier"}, {"resultId": 8790, "raceId": 381, "driverId": 110, "constructorId": 48, "number": "22", "grid": 18, "position": "\\N", "positionText": "R", "positionOrder": 19, "points": 0.0, "laps": 28, "time": "\\N", "milliseconds": "\\N", "fastestLap": "\\N", "rank": "\\N", "fastestLapTime": "\\N", "fastestLapSpeed": "\\N", "statusId": 86, "name": "Rial"}, {"resultId": 8791, "raceId": 381, "driverId": 145, "constructorId": 22, "number": "19", "grid": 5, "position": "\\N", "positionText": "R", "positionOrder": 20, "points": 0.0, "laps": 24, "time": "\\N", "milliseconds": "\\N", "fastestLap": "\\N", "rank": "\\N", "fastestLapTime": "\\N", "fastestLapSpeed": "\\N", "statusId": 25, "name": "Benetton"}, {"resultId": 8792, "raceId": 381, "driverId": 133, "constructorId": 35, "number": "36", "grid": 10, "position": "\\N", "positionText": "R", "positionOrder": 21, "points": 0.0, "laps": 22, "time": "\\N", "milliseconds": "\\N", "fastestLap": "\\N", "rank": "\\N", "fastestLapTime": "\\N", "fastestLapSpeed": "\\N", "statusId": 5, "name": "Dallara"}, {"resultId": 8793, "raceId": 381, "driverId": 140, "constructorId": 27, "number": "26", "grid": 24, "position": "\\N", "positionText": "R", "positionOrder": 22, "points": 0.0, "laps": 19, "time": "\\N", "milliseconds": "\\N", "fastestLap": "\\N", "rank": "\\N", "fastestLapTime": "\\N", "fastestLapSpeed": "\\N", "statusId": 37, "name": "Ligier"}, {"resultId": 8794, "raceId": 381, "driverId": 94, "constructorId": 18, "number": "23", "grid": 16, "position": "\\N", "positionText": "R", "positionOrder": 23, "points": 0.0, "laps": 8, "time": "\\N", "milliseconds": "\\N", "fastestLap": "\\N", "rank": "\\N", "fastestLapTime": "\\N", "fastestLapSpeed": "\\N", "statusId": 4, "name": "Minardi"}, {"resultId": 8795, "raceId": 381, "driverId": 166, "constructorId": 39, "number": "14", "grid": 23, "position": "\\N", "positionText": "R", "positionOrder": 24, "points": 0.0, "laps": 8, "time": "\\N", "milliseconds": "\\N", "fastestLap": "\\N", "rank": "\\N", "fastestLapTime": "\\N", "fastestLapSpeed": "\\N", "statusId": 4, "name": "AGS"}, {"resultId": 8796, "raceId": 381, "driverId": 122, "constructorId": 37, "number": "16", "grid": 4, "position": "\\N", "positionText": "R", "positionOrder": 25, "points": 0.0, "laps": 5, "time": "\\N", "milliseconds": "\\N", "fastestLap": "\\N", "rank": "\\N", "fastestLapTime": "\\N", "fastestLapSpeed": "\\N", "statusId": 5, "name": "March"}, {"resultId": 8797, "raceId": 381, "driverId": 156, "constructorId": 25, "number": "3", "grid": 21, "position": "\\N", "positionText": "R", "positionOrder": 26, "points": 0.0, "laps": 3, "time": "\\N", "milliseconds": "\\N", "fastestLap": "\\N", "rank": "\\N", "fastestLapTime": "\\N", "fastestLapSpeed": "\\N", "statusId": 5, "name": "Tyrrell"}, {"resultId": 8798, "raceId": 381, "driverId": 165, "constructorId": 44, "number": "32", "grid": 0, "position": "\\N", "positionText": "F", "positionOrder": 27, "points": 0.0, "laps": 0, "time": "\\N", "milliseconds": "\\N", "fastestLap": "\\N", "rank": "\\N", "fastestLapTime": "\\N", "fastestLapSpeed": "\\N", "statusId": 81, "name": "Euro Brun"}, {"resultId": 8799, "raceId": 381, "driverId": 146, "constructorId": 49, "number": "10", "grid": 0, "position": "\\N", "positionText": "F", "positionOrder": 28, "points": 0.0, "laps": 0, "time": "\\N", "milliseconds": "\\N", "fastestLap": "\\N", "rank": "\\N", "fastestLapTime": "\\N", "fastestLapSpeed": "\\N", "statusId": 81, "name": "Zakspeed"}, {"resultId": 8800, "raceId": 381, "driverId": 141, "constructorId": 25, "number": "4", "grid": 0, "position": "\\N", "positionText": "F", "positionOrder": 29, "points": 0.0, "laps": 0, "time": "\\N", "milliseconds": "\\N", "fastestLap": "\\N", "rank": "\\N", "fastestLapTime": "\\N", "fastestLapSpeed": "\\N", "statusId": 81, "name": "Tyrrell"}, {"resultId": 8801, "raceId": 381, "driverId": 160, "constructorId": 49, "number": "9", "grid": 0, "position": "\\N", "positionText": "F", "positionOrder": 30, "points": 0.0, "laps": 0, "time": "\\N", "milliseconds": "\\N", "fastestLap": "\\N", "rank": "\\N", "fastestLapTime": "\\N", "fastestLapSpeed": "\\N", "statusId": 81, "name": "Zakspeed"}, {"resultId": 8802, "raceId": 381, "driverId": 78, "constructorId": 45, "number": "21", "grid": 0, "position": "\\N", "positionText": "F", "positionOrder": 31, "points": 0.0, "laps": 0, "time": "\\N", "milliseconds": "\\N", "fastestLap": "\\N", "rank": "\\N", "fastestLapTime": "\\N", "fastestLapSpeed": "\\N", "statusId": 97, "name": "Osella"}]}}}}