{"MRData": {"RaceTable": {"Races": {"Results": [{"resultId": 21112, "raceId": 855, "driverId": 18, "constructorId": 1, "number": "4", "grid": 2, "position": "1", "positionText": "1", "positionOrder": 1, "points": 25.0, "laps": 53, "time": "1:30:53.427", "milliseconds": "5453427", "fastestLap": "52", "rank": "1", "fastestLapTime": "1:36.568", "fastestLapSpeed": "216.481", "statusId": 1}, {"resultId": 21113, "raceId": 855, "driverId": 4, "constructorId": 6, "number": "5", "grid": 5, "position": "2", "positionText": "2", "positionOrder": 2, "points": 18.0, "laps": 53, "time": "+1.160", "milliseconds": "5454587", "fastestLap": "50", "rank": "4", "fastestLapTime": "1:36.682", "fastestLapSpeed": "216.226", "statusId": 1}, {"resultId": 21114, "raceId": 855, "driverId": 20, "constructorId": 9, "number": "1", "grid": 1, "position": "3", "positionText": "3", "positionOrder": 3, "points": 15.0, "laps": 53, "time": "+2.006", "milliseconds": "5455433", "fastestLap": "52", "rank": "6", "fastestLapTime": "1:36.916", "fastestLapSpeed": "215.704", "statusId": 1}, {"resultId": 21115, "raceId": 855, "driverId": 17, "constructorId": 9, "number": "2", "grid": 6, "position": "4", "positionText": "4", "positionOrder": 4, "points": 12.0, "laps": 53, "time": "+8.071", "milliseconds": "5461498", "fastestLap": "47", "rank": "5", "fastestLapTime": "1:36.828", "fastestLapSpeed": "215.900", "statusId": 1}, {"resultId": 21116, "raceId": 855, "driverId": 1, "constructorId": 1, "number": "3", "grid": 3, "position": "5", "positionText": "5", "positionOrder": 5, "points": 10.0, "laps": 53, "time": "+24.268", "milliseconds": "5477695", "fastestLap": "49", "rank": "9", "fastestLapTime": "1:37.645", "fastestLapSpeed": "214.093", "statusId": 1}, {"resultId": 21117, "raceId": 855, "driverId": 30, "constructorId": 131, "number": "7", "grid": 8, "position": "6", "positionText": "6", "positionOrder": 6, "points": 8.0, "laps": 53, "time": "+27.120", "milliseconds": "5480547", "fastestLap": "53", "rank": "12", "fastestLapTime": "1:37.916", "fastestLapSpeed": "213.501", "statusId": 1}, {"resultId": 21118, "raceId": 855, "driverId": 13, "constructorId": 6, "number": "6", "grid": 4, "position": "7", "positionText": "7", "positionOrder": 7, "points": 6.0, "laps": 53, "time": "+28.240", "milliseconds": "5481667", "fastestLap": "50", "rank": "11", "fastestLapTime": "1:37.800", "fastestLapSpeed": "213.754", "statusId": 1}, {"resultId": 21119, "raceId": 855, "driverId": 815, "constructorId": 15, "number": "17", "grid": 17, "position": "8", "positionText": "8", "positionOrder": 8, "points": 4.0, "laps": 53, "time": "+39.377", "milliseconds": "5492804", "fastestLap": "39", "rank": "2", "fastestLapTime": "1:36.569", "fastestLapSpeed": "216.479", "statusId": 1}, {"resultId": 21120, "raceId": 855, "driverId": 808, "constructorId": 4, "number": "10", "grid": 10, "position": "9", "positionText": "9", "positionOrder": 9, "points": 2.0, "laps": 53, "time": "+42.607", "milliseconds": "5496034", "fastestLap": "47", "rank": "7", "fastestLapTime": "1:37.053", "fastestLapSpeed": "215.399", "statusId": 1}, {"resultId": 21121, "raceId": 855, "driverId": 3, "constructorId": 131, "number": "8", "grid": 23, "position": "10", "positionText": "10", "positionOrder": 10, "points": 1.0, "laps": 53, "time": "+44.322", "milliseconds": "5497749", "fastestLap": "50", "rank": "3", "fastestLapTime": "1:36.614", "fastestLapSpeed": "216.378", "statusId": 1}, {"resultId": 21122, "raceId": 855, "driverId": 16, "constructorId": 10, "number": "14", "grid": 11, "position": "11", "positionText": "11", "positionOrder": 11, "points": 0.0, "laps": 53, "time": "+54.447", "milliseconds": "5507874", "fastestLap": "43", "rank": "14", "fastestLapTime": "1:38.133", "fastestLapSpeed": "213.029", "statusId": 1}, {"resultId": 21123, "raceId": 855, "driverId": 814, "constructorId": 10, "number": "15", "grid": 12, "position": "12", "positionText": "12", "positionOrder": 12, "points": 0.0, "laps": 53, "time": "+1:02.326", "milliseconds": "5515753", "fastestLap": "43", "rank": "13", "fastestLapTime": "1:37.970", "fastestLapSpeed": "213.383", "statusId": 1}, {"resultId": 21124, "raceId": 855, "driverId": 155, "constructorId": 15, "number": "16", "grid": 7, "position": "13", "positionText": "13", "positionOrder": 13, "points": 0.0, "laps": 53, "time": "+1:03.705", "milliseconds": "5517132", "fastestLap": "44", "rank": "19", "fastestLapTime": "1:39.724", "fastestLapSpeed": "209.630", "statusId": 1}, {"resultId": 21125, "raceId": 855, "driverId": 813, "constructorId": 3, "number": "12", "grid": 14, "position": "14", "positionText": "14", "positionOrder": 14, "points": 0.0, "laps": 53, "time": "+1:04.194", "milliseconds": "5517621", "fastestLap": "50", "rank": "10", "fastestLapTime": "1:37.645", "fastestLapSpeed": "214.093", "statusId": 1}, {"resultId": 21126, "raceId": 855, "driverId": 153, "constructorId": 5, "number": "19", "grid": 16, "position": "15", "positionText": "15", "positionOrder": 15, "points": 0.0, "laps": 53, "time": "+1:06.623", "milliseconds": "5520050", "fastestLap": "41", "rank": "8", "fastestLapTime": "1:37.411", "fastestLapSpeed": "214.608", "statusId": 1}, {"resultId": 21127, "raceId": 855, "driverId": 811, "constructorId": 4, "number": "9", "grid": 9, "position": "16", "positionText": "16", "positionOrder": 16, "points": 0.0, "laps": 53, "time": "+1:12.628", "milliseconds": "5526055", "fastestLap": "42", "rank": "15", "fastestLapTime": "1:38.407", "fastestLapSpeed": "212.436", "statusId": 1}, {"resultId": 21128, "raceId": 855, "driverId": 22, "constructorId": 3, "number": "11", "grid": 13, "position": "17", "positionText": "17", "positionOrder": 17, "points": 0.0, "laps": 53, "time": "+1:14.191", "milliseconds": "5527618", "fastestLap": "53", "rank": "16", "fastestLapTime": "1:39.080", "fastestLapSpeed": "210.993", "statusId": 1}, {"resultId": 21129, "raceId": 855, "driverId": 5, "constructorId": 205, "number": "20", "grid": 18, "position": "18", "positionText": "18", "positionOrder": 18, "points": 0.0, "laps": 53, "time": "+1:27.824", "milliseconds": "5541251", "fastestLap": "50", "rank": "17", "fastestLapTime": "1:39.297", "fastestLapSpeed": "210.532", "statusId": 1}, {"resultId": 21130, "raceId": 855, "driverId": 15, "constructorId": 205, "number": "21", "grid": 19, "position": "19", "positionText": "19", "positionOrder": 19, "points": 0.0, "laps": 53, "time": "+1:36.140", "milliseconds": "5549567", "fastestLap": "49", "rank": "18", "fastestLapTime": "1:39.561", "fastestLapSpeed": "209.973", "statusId": 1}, {"resultId": 21131, "raceId": 855, "driverId": 10, "constructorId": 166, "number": "24", "grid": 21, "position": "20", "positionText": "20", "positionOrder": 20, "points": 0.0, "laps": 51, "time": "\\N", "milliseconds": "\\N", "fastestLap": "46", "rank": "21", "fastestLapTime": "1:41.704", "fastestLapSpeed": "205.549", "statusId": 12}, {"resultId": 21132, "raceId": 855, "driverId": 816, "constructorId": 166, "number": "25", "grid": 20, "position": "21", "positionText": "21", "positionOrder": 21, "points": 0.0, "laps": 51, "time": "\\N", "milliseconds": "\\N", "fastestLap": "45", "rank": "22", "fastestLapTime": "1:41.794", "fastestLapSpeed": "205.367", "statusId": 12}, {"resultId": 21133, "raceId": 855, "driverId": 817, "constructorId": 164, "number": "22", "grid": 22, "position": "22", "positionText": "22", "positionOrder": 22, "points": 0.0, "laps": 51, "time": "\\N", "milliseconds": "\\N", "fastestLap": "49", "rank": "20", "fastestLapTime": "1:41.437", "fastestLapSpeed": "206.090", "statusId": 12}, {"resultId": 21134, "raceId": 855, "driverId": 24, "constructorId": 164, "number": "23", "grid": 24, "position": "23", "positionText": "23", "positionOrder": 23, "points": 0.0, "laps": 50, "time": "\\N", "milliseconds": "\\N", "fastestLap": "37", "rank": "24", "fastestLapTime": "1:42.409", "fastestLapSpeed": "204.134", "statusId": 13}, {"resultId": 21135, "raceId": 855, "driverId": 67, "constructorId": 5, "number": "18", "grid": 15, "position": "\\N", "positionText": "R", "positionOrder": 24, "points": 0.0, "laps": 11, "time": "\\N", "milliseconds": "\\N", "fastestLap": "6", "rank": "23", "fastestLapTime": "1:42.107", "fastestLapSpeed": "204.738", "statusId": 36}]}}}}