{"MRData": {"RaceTable": {"Races": {"Results": [{"resultId": 17777, "raceId": 735, "driverId": 289, "constructorId": 66, "number": "14", "grid": 2, "position": "1", "positionText": "1", "positionOrder": 1, "points": 9.0, "laps": 86, "time": "2:29:08.4", "milliseconds": "8948400", "fastestLap": "\\N", "rank": "\\N", "fastestLapTime": "\\N", "fastestLapSpeed": "\\N", "statusId": 1}, {"resultId": 17778, "raceId": 735, "driverId": 386, "constructorId": 66, "number": "12", "grid": 3, "position": "2", "positionText": "2", "positionOrder": 2, "points": 6.0, "laps": 86, "time": "+29.8", "milliseconds": "8978200", "fastestLap": "\\N", "rank": "\\N", "fastestLapTime": "\\N", "fastestLapSpeed": "\\N", "statusId": 1}, {"resultId": 17779, "raceId": 735, "driverId": 360, "constructorId": 170, "number": "28", "grid": 4, "position": "3", "positionText": "3", "positionOrder": 3, "points": 4.0, "laps": 86, "time": "+57.8", "milliseconds": "9006200", "fastestLap": "\\N", "rank": "\\N", "fastestLapTime": "\\N", "fastestLapSpeed": "\\N", "statusId": 1}, {"resultId": 17780, "raceId": 735, "driverId": 435, "constructorId": 6, "number": "8", "grid": 10, "position": "4", "positionText": "4", "positionOrder": 4, "points": 3.0, "laps": 86, "time": "+58.2", "milliseconds": "9006600", "fastestLap": "\\N", "rank": "\\N", "fastestLapTime": "\\N", "fastestLapSpeed": "\\N", "statusId": 1}, {"resultId": 17781, "raceId": 735, "driverId": 394, "constructorId": 6, "number": "2", "grid": 18, "position": "5", "positionText": "5", "positionOrder": 5, "points": 2.0, "laps": 86, "time": "+1:31.3", "milliseconds": "9039700", "fastestLap": "\\N", "rank": "\\N", "fastestLapTime": "\\N", "fastestLapSpeed": "\\N", "statusId": 1}, {"resultId": 17782, "raceId": 735, "driverId": 347, "constructorId": 95, "number": "18", "grid": 9, "position": "6", "positionText": "6", "positionOrder": 6, "points": 1.0, "laps": 85, "time": "\\N", "milliseconds": "\\N", "fastestLap": "\\N", "rank": "\\N", "fastestLapTime": "\\N", "fastestLapSpeed": "\\N", "statusId": 11}, {"resultId": 17783, "raceId": 735, "driverId": 408, "constructorId": 170, "number": "30", "grid": 12, "position": "7", "positionText": "7", "positionOrder": 7, "points": 0.0, "laps": 85, "time": "\\N", "milliseconds": "\\N", "fastestLap": "\\N", "rank": "\\N", "fastestLapTime": "\\N", "fastestLapSpeed": "\\N", "statusId": 11}, {"resultId": 17784, "raceId": 735, "driverId": 385, "constructorId": 6, "number": "6", "grid": 17, "position": "8", "positionText": "8", "positionOrder": 8, "points": 0.0, "laps": 84, "time": "\\N", "milliseconds": "\\N", "fastestLap": "\\N", "rank": "\\N", "fastestLapTime": "\\N", "fastestLapSpeed": "\\N", "statusId": 12}, {"resultId": 17785, "raceId": 735, "driverId": 425, "constructorId": 172, "number": "24", "grid": 14, "position": "9", "positionText": "9", "positionOrder": 9, "points": 0.0, "laps": 84, "time": "\\N", "milliseconds": "\\N", "fastestLap": "\\N", "rank": "\\N", "fastestLapTime": "\\N", "fastestLapSpeed": "\\N", "statusId": 12}, {"resultId": 17786, "raceId": 735, "driverId": 430, "constructorId": 95, "number": "32", "grid": 20, "position": "10", "positionText": "10", "positionOrder": 10, "points": 0.0, "laps": 81, "time": "\\N", "milliseconds": "\\N", "fastestLap": "\\N", "rank": "\\N", "fastestLapTime": "\\N", "fastestLapSpeed": "\\N", "statusId": 15}, {"resultId": 17787, "raceId": 735, "driverId": 403, "constructorId": 6, "number": "10", "grid": 15, "position": "11", "positionText": "11", "positionOrder": 11, "points": 0.0, "laps": 81, "time": "\\N", "milliseconds": "\\N", "fastestLap": "\\N", "rank": "\\N", "fastestLapTime": "\\N", "fastestLapSpeed": "\\N", "statusId": 15}, {"resultId": 17788, "raceId": 735, "driverId": 418, "constructorId": 176, "number": "38", "grid": 6, "position": "12", "positionText": "12", "positionOrder": 12, "points": 0.0, "laps": 77, "time": "\\N", "milliseconds": "\\N", "fastestLap": "\\N", "rank": "\\N", "fastestLapTime": "\\N", "fastestLapSpeed": "\\N", "statusId": 19}, {"resultId": 17789, "raceId": 735, "driverId": 364, "constructorId": 95, "number": "16", "grid": 7, "position": "13", "positionText": "13", "positionOrder": 13, "points": 0.0, "laps": 66, "time": "\\N", "milliseconds": "\\N", "fastestLap": "\\N", "rank": "\\N", "fastestLapTime": "\\N", "fastestLapSpeed": "\\N", "statusId": 24}, {"resultId": 17790, "raceId": 735, "driverId": 454, "constructorId": 6, "number": "4", "grid": 11, "position": "14", "positionText": "14", "positionOrder": 14, "points": 0.0, "laps": 63, "time": "\\N", "milliseconds": "\\N", "fastestLap": "\\N", "rank": "\\N", "fastestLapTime": "\\N", "fastestLapSpeed": "\\N", "statusId": 80}, {"resultId": 17791, "raceId": 735, "driverId": 404, "constructorId": 172, "number": "40", "grid": 5, "position": "\\N", "positionText": "R", "positionOrder": 15, "points": 0.0, "laps": 45, "time": "\\N", "milliseconds": "\\N", "fastestLap": "\\N", "rank": "\\N", "fastestLapTime": "\\N", "fastestLapSpeed": "\\N", "statusId": 22}, {"resultId": 17792, "raceId": 735, "driverId": 341, "constructorId": 26, "number": "46", "grid": 8, "position": "\\N", "positionText": "R", "positionOrder": 16, "points": 0.0, "laps": 42, "time": "\\N", "milliseconds": "\\N", "fastestLap": "\\N", "rank": "\\N", "fastestLapTime": "\\N", "fastestLapSpeed": "\\N", "statusId": 5}, {"resultId": 17793, "raceId": 735, "driverId": 456, "constructorId": 26, "number": "44", "grid": 13, "position": "\\N", "positionText": "R", "positionOrder": 17, "points": 0.0, "laps": 41, "time": "\\N", "milliseconds": "\\N", "fastestLap": "\\N", "rank": "\\N", "fastestLapTime": "\\N", "fastestLapSpeed": "\\N", "statusId": 5}, {"resultId": 17794, "raceId": 735, "driverId": 401, "constructorId": 172, "number": "22", "grid": 16, "position": "\\N", "positionText": "R", "positionOrder": 18, "points": 0.0, "laps": 25, "time": "\\N", "milliseconds": "\\N", "fastestLap": "\\N", "rank": "\\N", "fastestLapTime": "\\N", "fastestLapSpeed": "\\N", "statusId": 6}, {"resultId": 17795, "raceId": 735, "driverId": 438, "constructorId": 99, "number": "48", "grid": 21, "position": "\\N", "positionText": "R", "positionOrder": 19, "points": 0.0, "laps": 18, "time": "\\N", "milliseconds": "\\N", "fastestLap": "\\N", "rank": "\\N", "fastestLapTime": "\\N", "fastestLapSpeed": "\\N", "statusId": 5}, {"resultId": 17796, "raceId": 735, "driverId": 427, "constructorId": 172, "number": "36", "grid": 19, "position": "\\N", "positionText": "R", "positionOrder": 20, "points": 0.0, "laps": 17, "time": "\\N", "milliseconds": "\\N", "fastestLap": "\\N", "rank": "\\N", "fastestLapTime": "\\N", "fastestLapSpeed": "\\N", "statusId": 10}, {"resultId": 17797, "raceId": 735, "driverId": 373, "constructorId": 172, "number": "20", "grid": 1, "position": "\\N", "positionText": "R", "positionOrder": 21, "points": 0.0, "laps": 12, "time": "\\N", "milliseconds": "\\N", "fastestLap": "\\N", "rank": "\\N", "fastestLapTime": "\\N", "fastestLapSpeed": "\\N", "statusId": 6}, {"resultId": 17798, "raceId": 735, "driverId": 464, "constructorId": 176, "number": "60", "grid": 0, "position": "\\N", "positionText": "F", "positionOrder": 22, "points": 0.0, "laps": 0, "time": "\\N", "milliseconds": "\\N", "fastestLap": "\\N", "rank": "\\N", "fastestLapTime": "\\N", "fastestLapSpeed": "\\N", "statusId": 81}, {"resultId": 17799, "raceId": 735, "driverId": 465, "constructorId": 97, "number": "56", "grid": 0, "position": "\\N", "positionText": "F", "positionOrder": 23, "points": 0.0, "laps": 0, "time": "\\N", "milliseconds": "\\N", "fastestLap": "\\N", "rank": "\\N", "fastestLapTime": "\\N", "fastestLapSpeed": "\\N", "statusId": 81}, {"resultId": 17800, "raceId": 735, "driverId": 460, "constructorId": 172, "number": "52", "grid": 0, "position": "\\N", "positionText": "F", "positionOrder": 24, "points": 0.0, "laps": 0, "time": "\\N", "milliseconds": "\\N", "fastestLap": "\\N", "rank": "\\N", "fastestLapTime": "\\N", "fastestLapSpeed": "\\N", "statusId": 81}, {"resultId": 17801, "raceId": 735, "driverId": 437, "constructorId": 170, "number": "62", "grid": 0, "position": "\\N", "positionText": "F", "positionOrder": 25, "points": 0.0, "laps": 0, "time": "\\N", "milliseconds": "\\N", "fastestLap": "\\N", "rank": "\\N", "fastestLapTime": "\\N", "fastestLapSpeed": "\\N", "statusId": 81}, {"resultId": 17802, "raceId": 735, "driverId": 346, "constructorId": 176, "number": "42", "grid": 0, "position": "\\N", "positionText": "F", "positionOrder": 26, "points": 0.0, "laps": 0, "time": "\\N", "milliseconds": "\\N", "fastestLap": "\\N", "rank": "\\N", "fastestLapTime": "\\N", "fastestLapSpeed": "\\N", "statusId": 81}, {"resultId": 17803, "raceId": 735, "driverId": 467, "constructorId": 172, "number": "54", "grid": 0, "position": "\\N", "positionText": "F", "positionOrder": 27, "points": 0.0, "laps": 0, "time": "\\N", "milliseconds": "\\N", "fastestLap": "\\N", "rank": "\\N", "fastestLapTime": "\\N", "fastestLapSpeed": "\\N", "statusId": 81}, {"resultId": 17804, "raceId": 735, "driverId": 444, "constructorId": 174, "number": "50", "grid": 0, "position": "\\N", "positionText": "F", "positionOrder": 28, "points": 0.0, "laps": 0, "time": "\\N", "milliseconds": "\\N", "fastestLap": "\\N", "rank": "\\N", "fastestLapTime": "\\N", "fastestLapSpeed": "\\N", "statusId": 81}, {"resultId": 17805, "raceId": 735, "driverId": 463, "constructorId": 172, "number": "26", "grid": 0, "position": "\\N", "positionText": "F", "positionOrder": 29, "points": 0.0, "laps": 0, "time": "\\N", "milliseconds": "\\N", "fastestLap": "\\N", "rank": "\\N", "fastestLapTime": "\\N", "fastestLapSpeed": "\\N", "statusId": 81}, {"resultId": 17806, "raceId": 735, "driverId": 439, "constructorId": 86, "number": "34", "grid": 0, "position": "\\N", "positionText": "F", "positionOrder": 30, "points": 0.0, "laps": 0, "time": "\\N", "milliseconds": "\\N", "fastestLap": "\\N", "rank": "\\N", "fastestLapTime": "\\N", "fastestLapSpeed": "\\N", "statusId": 81}, {"resultId": 17807, "raceId": 735, "driverId": 442, "constructorId": 177, "number": "58", "grid": 0, "position": "\\N", "positionText": "W", "positionOrder": 31, "points": 0.0, "laps": 0, "time": "\\N", "milliseconds": "\\N", "fastestLap": "\\N", "rank": "\\N", "fastestLapTime": "\\N", "fastestLapSpeed": "\\N", "statusId": 54}]}}}}