{"MRData": {"RaceTable": {"Races": {"Results": [{"resultId": 18791, "raceId": 779, "driverId": 579, "number": "2", "grid": 1, "position": "1", "positionText": "1", "positionOrder": 1, "points": 8.0, "laps": 77, "time": "3:07:46.4", "milliseconds": "11266400", "fastestLap": "\\N", "rank": "\\N", "fastestLapTime": "\\N", "fastestLapSpeed": "\\N", "statusId": 1, "Constructor": {"constructorId": 105, "name": "Maserati"}}, {"resultId": 18792, "raceId": 779, "driverId": 577, "number": "10", "grid": 3, "position": "2", "positionText": "2", "positionOrder": 2, "points": 7.0, "laps": 77, "time": "+50.8", "milliseconds": "11317200", "fastestLap": "\\N", "rank": "\\N", "fastestLapTime": "\\N", "fastestLapSpeed": "\\N", "statusId": 1, "Constructor": {"constructorId": 6, "name": "Ferrari"}}, {"resultId": 18793, "raceId": 779, "driverId": 581, "number": "12", "grid": 5, "position": "3", "positionText": "3", "positionOrder": 3, "points": 4.0, "laps": 77, "time": "+2:06.0", "milliseconds": "11392400", "fastestLap": "\\N", "rank": "\\N", "fastestLapTime": "\\N", "fastestLapSpeed": "\\N", "statusId": 1, "Constructor": {"constructorId": 6, "name": "Ferrari"}}, {"resultId": 18794, "raceId": 779, "driverId": 578, "number": "14", "grid": 7, "position": "4", "positionText": "4", "positionOrder": 4, "points": 3.0, "laps": 76, "time": "\\N", "milliseconds": "\\N", "fastestLap": "\\N", "rank": "\\N", "fastestLapTime": "\\N", "fastestLapSpeed": "\\N", "statusId": 11, "Constructor": {"constructorId": 6, "name": "Ferrari"}}, {"resultId": 18795, "raceId": 779, "driverId": 501, "number": "6", "grid": 4, "position": "5", "positionText": "5", "positionOrder": 5, "points": 2.0, "laps": 70, "time": "\\N", "milliseconds": "\\N", "fastestLap": "\\N", "rank": "\\N", "fastestLapTime": "\\N", "fastestLapSpeed": "\\N", "statusId": 17, "Constructor": {"constructorId": 105, "name": "Maserati"}}, {"resultId": 18796, "raceId": 779, "driverId": 554, "number": "4", "grid": 2, "position": "6", "positionText": "6", "positionOrder": 6, "points": 0.0, "laps": 69, "time": "\\N", "milliseconds": "\\N", "fastestLap": "\\N", "rank": "\\N", "fastestLapTime": "\\N", "fastestLapSpeed": "\\N", "statusId": 18, "Constructor": {"constructorId": 105, "name": "Maserati"}}, {"resultId": 18797, "raceId": 779, "driverId": 617, "number": "24", "grid": 15, "position": "7", "positionText": "7", "positionOrder": 7, "points": 0.0, "laps": 68, "time": "\\N", "milliseconds": "\\N", "fastestLap": "\\N", "rank": "\\N", "fastestLapTime": "\\N", "fastestLapSpeed": "\\N", "statusId": 19, "Constructor": {"constructorId": 87, "name": "Cooper"}}, {"resultId": 18798, "raceId": 779, "driverId": 496, "number": "8", "grid": 9, "position": "\\N", "positionText": "R", "positionOrder": 8, "points": 0.0, "laps": 30, "time": "\\N", "milliseconds": "\\N", "fastestLap": "\\N", "rank": "\\N", "fastestLapTime": "\\N", "fastestLapSpeed": "\\N", "statusId": 5, "Constructor": {"constructorId": 105, "name": "Maserati"}}, {"resultId": 18799, "raceId": 779, "driverId": 590, "number": "18", "grid": 10, "position": "\\N", "positionText": "R", "positionOrder": 9, "points": 0.0, "laps": 30, "time": "\\N", "milliseconds": "\\N", "fastestLap": "\\N", "rank": "\\N", "fastestLapTime": "\\N", "fastestLapSpeed": "\\N", "statusId": 38, "Constructor": {"constructorId": 118, "name": "Vanwall"}}, {"resultId": 18800, "raceId": 779, "driverId": 456, "number": "20", "grid": 6, "position": "\\N", "positionText": "R", "positionOrder": 10, "points": 0.0, "laps": 25, "time": "\\N", "milliseconds": "\\N", "fastestLap": "\\N", "rank": "\\N", "fastestLapTime": "\\N", "fastestLapSpeed": "\\N", "statusId": 5, "Constructor": {"constructorId": 118, "name": "Vanwall"}}, {"resultId": 18801, "raceId": 779, "driverId": 618, "number": "28", "grid": 12, "position": "\\N", "positionText": "R", "positionOrder": 11, "points": 0.0, "laps": 24, "time": "\\N", "milliseconds": "\\N", "fastestLap": "\\N", "rank": "\\N", "fastestLapTime": "\\N", "fastestLapSpeed": "\\N", "statusId": 7, "Constructor": {"constructorId": 66, "name": "BRM"}}, {"resultId": 18802, "raceId": 779, "driverId": 427, "number": "16", "grid": 8, "position": "\\N", "positionText": "R", "positionOrder": 12, "points": 0.0, "laps": 23, "time": "\\N", "milliseconds": "\\N", "fastestLap": "\\N", "rank": "\\N", "fastestLapTime": "\\N", "fastestLapSpeed": "\\N", "statusId": 10, "Constructor": {"constructorId": 6, "name": "Ferrari"}}, {"resultId": 18803, "raceId": 779, "driverId": 356, "number": "22", "grid": 13, "position": "\\N", "positionText": "R", "positionOrder": 13, "points": 0.0, "laps": 4, "time": "\\N", "milliseconds": "\\N", "fastestLap": "\\N", "rank": "\\N", "fastestLapTime": "\\N", "fastestLapSpeed": "\\N", "statusId": 3, "Constructor": {"constructorId": 87, "name": "Cooper"}}, {"resultId": 18804, "raceId": 779, "driverId": 547, "number": "30", "grid": 14, "position": "\\N", "positionText": "R", "positionOrder": 14, "points": 0.0, "laps": 4, "time": "\\N", "milliseconds": "\\N", "fastestLap": "\\N", "rank": "\\N", "fastestLapTime": "\\N", "fastestLapSpeed": "\\N", "statusId": 86, "Constructor": {"constructorId": 105, "name": "Maserati"}}, {"resultId": 18805, "raceId": 779, "driverId": 541, "number": "26", "grid": 11, "position": "\\N", "positionText": "R", "positionOrder": 15, "points": 0.0, "laps": 2, "time": "\\N", "milliseconds": "\\N", "fastestLap": "\\N", "rank": "\\N", "fastestLapTime": "\\N", "fastestLapSpeed": "\\N", "statusId": 3, "Constructor": {"constructorId": 66, "name": "BRM"}}, {"resultId": 20290, "raceId": 779, "driverId": 356, "number": "24", "grid": 15, "position": "7", "positionText": "7", "positionOrder": 7, "points": 0.0, "laps": 68, "time": "\\N", "milliseconds": "\\N", "fastestLap": "\\N", "rank": "\\N", "fastestLapTime": "\\N", "fastestLapSpeed": "\\N", "statusId": 19, "Constructor": {"constructorId": 87, "name": "Cooper"}}]}}}}