{"MRData": {"RaceTable": {"Races": {"Results": [{"resultId": 14109, "raceId": 574, "driverId": 231, "constructorId": 1, "number": "11", "grid": 1, "position": "1", "positionText": "1", "positionOrder": 1, "points": 9.0, "laps": 59, "time": "1:42:40.742", "milliseconds": "6160742", "fastestLap": "\\N", "rank": "\\N", "fastestLapTime": "\\N", "fastestLapSpeed": "\\N", "statusId": 1}, {"resultId": 14110, "raceId": 574, "driverId": 222, "constructorId": 25, "number": "3", "grid": 2, "position": "2", "positionText": "2", "positionOrder": 2, "points": 6.0, "laps": 59, "time": "+8.030", "milliseconds": "6168772", "fastestLap": "\\N", "rank": "\\N", "fastestLapTime": "\\N", "fastestLapSpeed": "\\N", "statusId": 1}, {"resultId": 14111, "raceId": 574, "driverId": 182, "constructorId": 6, "number": "1", "grid": 5, "position": "3", "positionText": "3", "positionOrder": 3, "points": 4.0, "laps": 59, "time": "+1:02.324", "milliseconds": "6223066", "fastestLap": "\\N", "rank": "\\N", "fastestLapTime": "\\N", "fastestLapSpeed": "\\N", "statusId": 1}, {"resultId": 14112, "raceId": 574, "driverId": 200, "constructorId": 1, "number": "12", "grid": 17, "position": "4", "positionText": "4", "positionOrder": 4, "points": 3.0, "laps": 59, "time": "+1:02.458", "milliseconds": "6223200", "fastestLap": "\\N", "rank": "\\N", "fastestLapTime": "\\N", "fastestLapSpeed": "\\N", "statusId": 1}, {"resultId": 14113, "raceId": 574, "driverId": 233, "constructorId": 37, "number": "34", "grid": 6, "position": "5", "positionText": "5", "positionOrder": 5, "points": 2.0, "laps": 59, "time": "+1:07.978", "milliseconds": "6228720", "fastestLap": "\\N", "rank": "\\N", "fastestLapTime": "\\N", "fastestLapSpeed": "\\N", "statusId": 1}, {"resultId": 14114, "raceId": 574, "driverId": 187, "constructorId": 67, "number": "28", "grid": 8, "position": "6", "positionText": "6", "positionOrder": 6, "points": 1.0, "laps": 59, "time": "+1:08.190", "milliseconds": "6228932", "fastestLap": "\\N", "rank": "\\N", "fastestLapTime": "\\N", "fastestLapSpeed": "\\N", "statusId": 1}, {"resultId": 14115, "raceId": 574, "driverId": 223, "constructorId": 6, "number": "2", "grid": 14, "position": "7", "positionText": "7", "positionOrder": 7, "points": 0.0, "laps": 58, "time": "\\N", "milliseconds": "\\N", "fastestLap": "\\N", "rank": "\\N", "fastestLapTime": "\\N", "fastestLapSpeed": "\\N", "statusId": 11}, {"resultId": 14116, "raceId": 574, "driverId": 178, "constructorId": 63, "number": "19", "grid": 18, "position": "8", "positionText": "8", "positionOrder": 8, "points": 0.0, "laps": 58, "time": "\\N", "milliseconds": "\\N", "fastestLap": "\\N", "rank": "\\N", "fastestLapTime": "\\N", "fastestLapSpeed": "\\N", "statusId": 11}, {"resultId": 14117, "raceId": 574, "driverId": 224, "constructorId": 56, "number": "30", "grid": 15, "position": "9", "positionText": "9", "positionOrder": 9, "points": 0.0, "laps": 57, "time": "\\N", "milliseconds": "\\N", "fastestLap": "\\N", "rank": "\\N", "fastestLapTime": "\\N", "fastestLapSpeed": "\\N", "statusId": 12}, {"resultId": 14118, "raceId": 574, "driverId": 197, "constructorId": 58, "number": "17", "grid": 16, "position": "10", "positionText": "10", "positionOrder": 10, "points": 0.0, "laps": 57, "time": "\\N", "milliseconds": "\\N", "fastestLap": "\\N", "rank": "\\N", "fastestLapTime": "\\N", "fastestLapSpeed": "\\N", "statusId": 12}, {"resultId": 14119, "raceId": 574, "driverId": 239, "constructorId": 63, "number": "18", "grid": 24, "position": "11", "positionText": "11", "positionOrder": 11, "points": 0.0, "laps": 57, "time": "\\N", "milliseconds": "\\N", "fastestLap": "\\N", "rank": "\\N", "fastestLapTime": "\\N", "fastestLapSpeed": "\\N", "statusId": 12}, {"resultId": 14120, "raceId": 574, "driverId": 237, "constructorId": 64, "number": "25", "grid": 22, "position": "12", "positionText": "12", "positionOrder": 12, "points": 0.0, "laps": 57, "time": "\\N", "milliseconds": "\\N", "fastestLap": "\\N", "rank": "\\N", "fastestLapTime": "\\N", "fastestLapSpeed": "\\N", "statusId": 12}, {"resultId": 14121, "raceId": 574, "driverId": 229, "constructorId": 64, "number": "24", "grid": 21, "position": "13", "positionText": "13", "positionOrder": 13, "points": 0.0, "laps": 54, "time": "\\N", "milliseconds": "\\N", "fastestLap": "\\N", "rank": "\\N", "fastestLapTime": "\\N", "fastestLapSpeed": "\\N", "statusId": 15}, {"resultId": 14122, "raceId": 574, "driverId": 286, "constructorId": 59, "number": "21", "grid": 23, "position": "14", "positionText": "14", "positionOrder": 14, "points": 0.0, "laps": 54, "time": "\\N", "milliseconds": "\\N", "fastestLap": "\\N", "rank": "\\N", "fastestLapTime": "\\N", "fastestLapSpeed": "\\N", "statusId": 15}, {"resultId": 14123, "raceId": 574, "driverId": 280, "constructorId": 63, "number": "38", "grid": 26, "position": "\\N", "positionText": "N", "positionOrder": 15, "points": 0.0, "laps": 48, "time": "\\N", "milliseconds": "\\N", "fastestLap": "\\N", "rank": "\\N", "fastestLapTime": "\\N", "fastestLapSpeed": "\\N", "statusId": 62}, {"resultId": 14124, "raceId": 574, "driverId": 252, "constructorId": 58, "number": "16", "grid": 9, "position": "\\N", "positionText": "R", "positionOrder": 16, "points": 0.0, "laps": 45, "time": "\\N", "milliseconds": "\\N", "fastestLap": "\\N", "rank": "\\N", "fastestLapTime": "\\N", "fastestLapSpeed": "\\N", "statusId": 5}, {"resultId": 14125, "raceId": 574, "driverId": 230, "constructorId": 37, "number": "9", "grid": 12, "position": "\\N", "positionText": "R", "positionOrder": 17, "points": 0.0, "laps": 34, "time": "\\N", "milliseconds": "\\N", "fastestLap": "\\N", "rank": "\\N", "fastestLapTime": "\\N", "fastestLapSpeed": "\\N", "statusId": 27}, {"resultId": 14126, "raceId": 574, "driverId": 172, "constructorId": 27, "number": "26", "grid": 4, "position": "\\N", "positionText": "R", "positionOrder": 18, "points": 0.0, "laps": 34, "time": "\\N", "milliseconds": "\\N", "fastestLap": "\\N", "rank": "\\N", "fastestLapTime": "\\N", "fastestLapSpeed": "\\N", "statusId": 27}, {"resultId": 14127, "raceId": 574, "driverId": 250, "constructorId": 204, "number": "8", "grid": 10, "position": "\\N", "positionText": "R", "positionOrder": 19, "points": 0.0, "laps": 31, "time": "\\N", "milliseconds": "\\N", "fastestLap": "\\N", "rank": "\\N", "fastestLapTime": "\\N", "fastestLapSpeed": "\\N", "statusId": 4}, {"resultId": 14128, "raceId": 574, "driverId": 256, "constructorId": 204, "number": "7", "grid": 13, "position": "\\N", "positionText": "R", "positionOrder": 20, "points": 0.0, "laps": 30, "time": "\\N", "milliseconds": "\\N", "fastestLap": "\\N", "rank": "\\N", "fastestLapTime": "\\N", "fastestLapSpeed": "\\N", "statusId": 22}, {"resultId": 14129, "raceId": 574, "driverId": 207, "constructorId": 32, "number": "5", "grid": 11, "position": "\\N", "positionText": "R", "positionOrder": 21, "points": 0.0, "laps": 23, "time": "\\N", "milliseconds": "\\N", "fastestLap": "\\N", "rank": "\\N", "fastestLapTime": "\\N", "fastestLapSpeed": "\\N", "statusId": 22}, {"resultId": 14130, "raceId": 574, "driverId": 235, "constructorId": 57, "number": "22", "grid": 19, "position": "\\N", "positionText": "R", "positionOrder": 22, "points": 0.0, "laps": 14, "time": "\\N", "milliseconds": "\\N", "fastestLap": "\\N", "rank": "\\N", "fastestLapTime": "\\N", "fastestLapSpeed": "\\N", "statusId": 3}, {"resultId": 14131, "raceId": 574, "driverId": 255, "constructorId": 32, "number": "6", "grid": 20, "position": "\\N", "positionText": "R", "positionOrder": 23, "points": 0.0, "laps": 13, "time": "\\N", "milliseconds": "\\N", "fastestLap": "\\N", "rank": "\\N", "fastestLapTime": "\\N", "fastestLapSpeed": "\\N", "statusId": 5}, {"resultId": 14132, "raceId": 574, "driverId": 238, "constructorId": 37, "number": "10", "grid": 3, "position": "\\N", "positionText": "R", "positionOrder": 24, "points": 0.0, "laps": 12, "time": "\\N", "milliseconds": "\\N", "fastestLap": "\\N", "rank": "\\N", "fastestLapTime": "\\N", "fastestLapSpeed": "\\N", "statusId": 22}, {"resultId": 14133, "raceId": 574, "driverId": 232, "constructorId": 59, "number": "20", "grid": 25, "position": "\\N", "positionText": "R", "positionOrder": 25, "points": 0.0, "laps": 9, "time": "\\N", "milliseconds": "\\N", "fastestLap": "\\N", "rank": "\\N", "fastestLapTime": "\\N", "fastestLapSpeed": "\\N", "statusId": 3}, {"resultId": 14134, "raceId": 574, "driverId": 221, "constructorId": 25, "number": "4", "grid": 7, "position": "\\N", "positionText": "R", "positionOrder": 26, "points": 0.0, "laps": 7, "time": "\\N", "milliseconds": "\\N", "fastestLap": "\\N", "rank": "\\N", "fastestLapTime": "\\N", "fastestLapSpeed": "\\N", "statusId": 106}, {"resultId": 14135, "raceId": 574, "driverId": 285, "constructorId": 25, "number": "39", "grid": 0, "position": "\\N", "positionText": "F", "positionOrder": 27, "points": 0.0, "laps": 0, "time": "\\N", "milliseconds": "\\N", "fastestLap": "\\N", "rank": "\\N", "fastestLapTime": "\\N", "fastestLapSpeed": "\\N", "statusId": 81}]}}}}